Metadata-Version: 1.2
Name: corella-lib
Version: 0.1.1
Summary: Client library for Taggles Corella module
Home-page: http://corella.taggle.com.au
Author: Oktay Sancak
Author-email: oktay.sancak@taggle.com.au
License: Apache License Version 2.0
Keywords: taggle corella_lib iot lpwan serial x-bee
Platform: UNKNOWN
Classifier: Programming Language :: Python :: 3.5
Classifier: Programming Language :: Python :: 3.6
Requires-Python: >=3.5
